README.md
setup.py
cli/__init__.py
cli/rfid_cli.py
pyrfidhid.egg-info/PKG-INFO
pyrfidhid.egg-info/SOURCES.txt
pyrfidhid.egg-info/dependency_links.txt
pyrfidhid.egg-info/entry_points.txt
pyrfidhid.egg-info/requires.txt
pyrfidhid.egg-info/top_level.txt
rfidhid/__init__.py
rfidhid/core.py
rfidhid/test_core.py
rfidhid/usb_hid.py