Metadata-Version: 1.0
Name: pyrfidhid
Version: 1.1.4
Summary: Library to control 125Khz RFID USB HID Device
Home-page: https://github.com/charlysan/pyrfidhid/
Author: charlysan
Author-email: chrlysn0@gmail.com
License: MIT
Platform: UNKNOWN
